pywinput/__init__.py
pywinput/constants.py
pywinput/error.log
pywinput/exceptions.py
pywinput/logger.py
pywinput/structures.py
pywinput/win_mouse.py
pywinput/window.py
pywinput/window_class.py
pywinput-0.1.0.dist-info/LICENSE
pywinput-0.1.0.dist-info/WHEEL
pywinput-0.1.0.dist-info/METADATA
pywinput-0.1.0.dist-info/RECORD
